bannercommon/__init__.py
bannercommon/exceptions.py
bannercommon-0.0.0.dev1.dist-info/METADATA
bannercommon-0.0.0.dev1.dist-info/WHEEL
bannercommon-0.0.0.dev1.dist-info/top_level.txt
bannercommon-0.0.0.dev1.dist-info/RECORD
