Metadata-Version: 2.1
Name: bannercommon
Version: 0.0.0.dev1
Summary: UNKNOWN
Home-page: UNKNOWN
License: UNKNOWN
Platform: UNKNOWN
Requires-Python: >=3.6, <4
